metric_emitter/__init__.py
metric_emitter/_version.py
metric_emitter/emitter.py
lf_metric_emitter-0.0.3.dist-info/LICENSE
lf_metric_emitter-0.0.3.dist-info/METADATA
lf_metric_emitter-0.0.3.dist-info/WHEEL
lf_metric_emitter-0.0.3.dist-info/top_level.txt
lf_metric_emitter-0.0.3.dist-info/RECORD
