Metadata-Version: 2.1
Name: lf-metric-emitter
Version: 0.0.3
Author-email: LINCC Frameworks <name@you.com>
License: MIT License
Classifier: Development Status :: 4 - Beta
Classifier: License :: OSI Approved :: MIT License
Classifier: Intended Audience :: Developers
Classifier: Intended Audience :: Science/Research
Classifier: Operating System :: OS Independent
Classifier: Programming Language :: Python
License-File: LICENSE
Provides-Extra: dev
Requires-Dist: pytest ; extra == 'dev'
Requires-Dist: pytest-cov ; extra == 'dev'
Requires-Dist: pre-commit ; extra == 'dev'
Requires-Dist: sphinx (==6.1.3) ; extra == 'dev'
Requires-Dist: sphinx-rtd-theme (==1.2.0) ; extra == 'dev'
Requires-Dist: sphinx-autoapi (==2.0.1) ; extra == 'dev'
Requires-Dist: black ; extra == 'dev'
